{"Abra":	1,
"Aipom":	1,
"Amaura":	1,
"Anorith":	1,
"Applin":	1,
"Arbok":	1,
"Archen":	1,
"Aron":	1,
"Arrokuda":	1,
"Axew":	1,
"Azurill":	1,
"Bagon":	1,
"Baltoy":	1,
"Banette":	1,
"Barboach":	1,
"Bastiodon":	1,
"Bayleef":	1,
"Beautifly":	1,
"Beedrill":	1,
"Beldum":	1,
"Bellsprout":	1,
"Bergmite":	1,
"Bidoof":	1,
"Binacle":	1,
"Blipbug":	1,
"Blitzle":	1,
"Boldore":	1,
"Bonsly":	1,
"Bounsweet":	1,
"Braixen":	1,
"Brionne":	1,
"Bronzor":	1,
"Budew":	1,
"Buizel":	1,
"Bulbasaur":	1,
"Buneary":	1,
"Bunnelby":	1,
"Burmy":	1,
"Butterfree":	1,
"Cacnea":	1,
"Carkol":	1,
"Carnivine":	1,
"Carvanha":	1,
"Cascoon":	1,
"Castform":	1,
"Caterpie":	1,
"Charjabug":	1,
"Charmander":	1,
"Charmeleon":	1,
"Chatot":	1,
"Cherrim":	1,
"Cherubi":	1,
"Chespin":	1,
"Chewtle":	1,
"Chikorita":	1,
"Chimchar":	1,
"Chinchou":	1,
"Chingling":	1,
"Clamperl":	1,
"Clauncher":	1,
"Cleffa":	1,
"Clobbopus":	1,
"Combee":	1,
"Corphish":	1,
"Corsola":	1,
"Corvisquire":	1,
"Cosmoem":	1,
"Cosmog":	1,
"Cottonee":	1,
"Crabrawler":	1,
"Cranidos":	1,
"Croagunk":	1,
"Croconaw":	1,
"Cubchoo":	1,
"Cubone":	1,
"Cufant":	1,
"Cutiefly":	1,
"Cyndaquil":	1,
"Dartrix":	1,
"Darumaka":	1,
"Darumaka-Galar":	1,
"Dedenne":	1,
"Deerling":	1,
"Deino":	1,
"Delcatty":	1,
"Delibird":	1,
"Dewgong":	1,
"Dewott":	1,
"Dewpider":	1,
"Diglett":	1,
"Diglett-Alola":	1,
"Doduo":	1,
"Dragonair":	1,
"Dratini":	1,
"Dreepy":	1,
"Drifloon":	1,
"Drilbur":	1,
"Drizzile":	1,
"Drowzee":	1,
"Ducklett":	1,
"Duskull":	1,
"Dustox":	1,
"Dwebble":	1,
"Eelektrik":	1,
"Eevee":	1,
"Ekans":	1,
"Electrike":	1,
"Elekid":	1,
"Elgyem":	1,
"Emolga":	1,
"Espurr":	1,
"Exeggcute":	1,
"Farfetch'd":	1,
"Farfetch'd-Galar":	1,
"Fearow":	1,
"Feebas":	1,
"Fennekin":	1,
"Finneon":	1,
"Flaaffy":	1,
"Flabébé":	1,
"Fletchinder":	1,
"Fletchling":	1,
"Floette":	1,
"Fomantis":	1,
"Foongus":	1,
"Fraxure":	1,
"Frillish":	1,
"Froakie":	1,
"Furfrou":	1,
"Furret":	1,
"Gabite":	1,
"Gastly":	1,
"Geodude":	1,
"Geodude-Alola":	1,
"Gible":	1,
"Girafarig":	1,
"Glalie":	1,
"Glameow":	1,
"Gloom":	1,
"Goldeen":	1,
"Golem":	1,
"Golett":	1,
"Goomy":	1,
"Gossifleur":	1,
"Gothita":	1,
"Gothorita":	1,
"Graveler":	1,
"Graveler-Alola":	1,
"Grimer":	1,
"Grimer-Alola":	1,
"Grookey":	1,
"Grovyle":	1,
"Growlithe":	1,
"Grubbin":	1,
"Gulpin":	1,
"Hakamo-o":	1,
"Happiny":	1,
"Hatenna":	1,
"Hattrem":	1,
"Heatmor":	1,
"Helioptile":	1,
"Herdier":	1,
"Honedge":	1,
"Hoothoot":	1,
"Hoppip":	1,
"Horsea":	1,
"Houndour":	1,
"Igglybuff":	1,
"Illumise":	1,
"Impidimp":	1,
"Inkay":	1,
"Ivysaur":	1,
"Jangmo-o":	1,
"Jigglypuff":	1,
"Joltik":	1,
"Kabuto":	1,
"Kakuna":	1,
"Karrablast":	1,
"Kirlia":	1,
"Klang":	1,
"Klink":	1,
"Koffing":	1,
"Krabby":	1,
"Kricketot":	1,
"Kricketune":	1,
"Krokorok":	1,
"Kubfu":	1,
"Lairon":	1,
"Lampent":	1,
"Larvesta":	1,
"Larvitar":	1,
"Ledian":	1,
"Ledyba":	1,
"Lileep":	1,
"Lillipup":	1,
"Litleo":	1,
"Litten":	1,
"Litwick":	1,
"Lombre":	1,
"Lotad":	1,
"Loudred":	1,
"Lumineon":	1,
"Lunatone":	1,
"Luvdisc":	1,
"Luxio":	1,
"Machoke":	1,
"Machop":	1,
"Magby":	1,
"Magcargo":	1,
"Magikarp":	1,
"Magnemite":	1,
"Makuhita":	1,
"Mankey":	1,
"Mantyke":	1,
"Maractus":	1,
"Mareanie":	1,
"Mareep":	1,
"Marill":	1,
"Marowak":	1,
"Marshtomp":	1,
"Meditite":	1,
"Meltan":	1,
"Meowth":	1,
"Meowth-Alola":	1,
"Meowth-Galar":	1,
"Metang":	1,
"Metapod":	1,
"Mienfoo":	1,
"Mightyena":	1,
"Milcery":	1,
"Mime Jr.":	1,
"Minccino":	1,
"Minun":	1,
"Monferno":	1,
"Morelull":	1,
"Morgrem":	1,
"Mothim":	1,
"Mudbray":	1,
"Mudkip":	1,
"Munna":	1,
"Murkrow":	1,
"Natu":	1,
"Nickit":	1,
"Nidoran♀":	1,
"Nidoran♂":	1,
"Nidorina":	1,
"Nidorino":	1,
"Nincada":	1,
"Noibat":	1,
"Nosepass":	1,
"Numel":	1,
"Nuzleaf":	1,
"Octillery":	1,
"Oddish":	1,
"Omanyte":	1,
"Onix":	1,
"Oshawott":	1,
"Pachirisu":	1,
"Palpitoad":	1,
"Pancham":	1,
"Panpour":	1,
"Pansage":	1,
"Pansear":	1,
"Paras":	1,
"Parasect":	1,
"Patrat":	1,
"Pawniard":	1,
"Persian":	1,
"Petilil":	1,
"Phanpy":	1,
"Phantump":	1,
"Phione":	1,
"Pichu":	1,
"Pidgeot":	1,
"Pidgeotto":	1,
"Pidgey":	1,
"Pidove":	1,
"Pignite":	1,
"Pikachu":	1,
"Pikipek":	1,
"Pineco":	1,
"Piplup":	1,
"Plusle":	1,
"Poipole":	1,
"Poliwag":	1,
"Poliwhirl":	1,
"Ponyta":	1,
"Ponyta-Galar":	1,
"Poochyena":	1,
"Popplio":	1,
"Porygon":	1,
"Psyduck":	1,
"Pumpkaboo":	1,
"Pupitar":	1,
"Purrloin":	1,
"Quilava":	1,
"Ralts":	1,
"Rattata":	1,
"Rattata-Alola":	1,
"Relicanth":	1,
"Remoraid":	1,
"Rhyhorn":	1,
"Riolu":	1,
"Rockruff":	1,
"Roggenrola":	1,
"Rolycoly":	1,
"Rookidee":	1,
"Rowlet":	1,
"Rufflet":	1,
"Salandit":	1,
"Sandile":	1,
"Sandshrew":	1,
"Sandshrew-Alola":	1,
"Sandygast":	1,
"Scatterbug":	1,
"Scorbunny":	1,
"Scraggy":	1,
"Seadra":	1,
"Seaking":	1,
"Sealeo":	1,
"Seedot":	1,
"Seel":	1,
"Sentret":	1,
"Servine":	1,
"Seviper":	1,
"Sewaddle":	1,
"Shedinja":	1,
"Shelgon":	1,
"Shellder":	1,
"Shellos":	1,
"Shelmet":	1,
"Shieldon":	1,
"Shinx":	1,
"Shroomish":	1,
"Shuppet":	1,
"Silcoon":	1,
"Silicobra":	1,
"Sinistea":	1,
"Sizzlipede":	1,
"Skiddo":	1,
"Skiploom":	1,
"Skitty":	1,
"Skorupi":	1,
"Skrelp":	1,
"Skwovet":	1,
"Slakoth":	1,
"Sliggoo":	1,
"Slowpoke":	1,
"Slowpoke-Galar":	1,
"Slugma":	1,
"Smoochum":	1,
"Snivy":	1,
"Snom":	1,
"Snorunt":	1,
"Snover":	1,
"Snubbull":	1,
"Sobble":	1,
"Solosis":	1,
"Solrock":	1,
"Spearow":	1,
"Spewpa":	1,
"Spheal":	1,
"Spinarak":	1,
"Spinda":	1,
"Spoink":	1,
"Spritzee":	1,
"Squirtle":	1,
"Stantler":	1,
"Staravia":	1,
"Starly":	1,
"Staryu":	1,
"Steenee":	1,
"Stufful":	1,
"Stunky":	1,
"Sudowoodo":	1,
"Sunflora":	1,
"Sunkern":	1,
"Surskit":	1,
"Swablu":	1,
"Swadloon":	1,
"Swalot":	1,
"Swinub":	1,
"Swirlix":	1,
"Taillow":	1,
"Teddiursa":	1,
"Tentacool":	1,
"Tepig":	1,
"Timburr":	1,
"Tirtouga":	1,
"Togepi":	1,
"Torchic":	1,
"Torracat":	1,
"Totodile":	1,
"Toxel":	1,
"Tranquill":	1,
"Trapinch":	1,
"Treecko":	1,
"Tropius":	1,
"Trubbish":	1,
"Trumbeak":	1,
"Turtwig":	1,
"Tympole":	1,
"Tynamo":	1,
"Tyrogue":	1,
"Tyrunt":	1,
"Vanillish":	1,
"Vanillite":	1,
"Venipede":	1,
"Venonat":	1,
"Vespiquen":	1,
"Vibrava":	1,
"Vigoroth":	1,
"Volbeat":	1,
"Voltorb":	1,
"Vulpix":	1,
"Vulpix-Alola":	1,
"Wailmer":	1,
"Wailord":	1,
"Watchog":	1,
"Weedle":	1,
"Weepinbell":	1,
"Whirlipede":	1,
"Whismur":	1,
"Wimpod":	1,
"Wingull":	1,
"Woobat":	1,
"Wooloo":	1,
"Wooper":	1,
"Wormadam":	1,
"Wurmple":	1,
"Wynaut":	1,
"Yamask":	1,
"Yamask-Galar":	1,
"Yamper":	1,
"Yanma":	1,
"Yungoos":	1,
"Zigzagoon":	1,
"Zigzagoon-Galar":	1,
"Zorua":	1,
"Zubat":	1,
"Zweilous":	1,
"Altaria":	2,
"Ariados":	2,
"Banette-Mega":	2,
"Basculin":	2,
"Beartic":	2,
"Bellossom":	2,
"Bibarel":	2,
"Cacturne":	2,
"Calyrex":	2,
"Camerupt":	2,
"Chimecho":	2,
"Combusken":	2,
"Dottler":	2,
"Drakloak":	2,
"Dunsparce":	2,
"Duosion":	2,
"Electrode":	2,
"Exeggutor":	2,
"Frogadier":	2,
"Glaceon":	2,
"Greedent":	2,
"Grotle":	2,
"Grumpig":	2,
"Gumshoos":	2,
"Hippopotas":	2,
"Hypno":	2,
"Jumpluff":	2,
"Kadabra":	2,
"Leavanny":	2,
"Lickitung":	2,
"Lilligant":	2,
"Linoone-Galar":	2,
"Lopunny":	2,
"Magmar":	2,
"Masquerain":	2,
"Mawile":	2,
"Meganium":	2,
"Meowstic":	2,
"Mr. Mime":	2,
"Muk":	2,
"Ninjask":	2,
"Noctowl":	2,
"Oranguru":	2,
"Prinplup":	2,
"Probopass":	2,
"Purugly":	2,
"Raboot":	2,
"Raticate":	2,
"Raticate-Alola":	2,
"Slaking":	2,
"Swanna":	2,
"Thievul":	2,
"Toucannon":	2,
"Unfezant":	2,
"Wartortle":	2,
"Whiscash":	2,
"Wigglytuff":	2,
"Zebstrika":	2,
"Ampharos":	3,
"Armaldo":	3,
"Beheeyem":	3,
"Bouffalant":	3,
"Carbink":	3,
"Clefairy":	3,
"Corsola-Galar":	3,
"Crabominable":	3,
"Cradily":	3,
"Cramorant":	3,
"Eiscue":	3,
"Eldegoss":	3,
"Electabuzz":	3,
"Falinks":	3,
"Flareon":	3,
"Gogoat":	3,
"Golduck":	3,
"Golem-Alola":	3,
"Gorebyss":	3,
"Grapploct":	3,
"Haunter":	3,
"Huntail":	3,
"Jynx":	3,
"Kingler":	3,
"Klinklang":	3,
"Leafeon":	3,
"Malamar":	3,
"Manectric":	3,
"Misdreavus":	3,
"Munchlax":	3,
"Pinsir":	3,
"Pyukumuku":	3,
"Quilladin":	3,
"Rampardos":	3,
"Samurott":	3,
"Sawsbuck":	3,
"Shiftry":	3,
"Shiinotic":	3,
"Shuckle":	3,
"Simipour":	3,
"Simisage":	3,
"Simisear":	3,
"Smeargle":	3,
"Stonjourner":	3,
"Stoutland":	3,
"Thwackey":	3,
"Togedemaru":	3,
"Torterra":	3,
"Turtonator":	3,
"Typhlosion":	3,
"Vivillon":	3,
"Vullaby":	3,
"Walrein":	3,
"Wishiwashi":	3,
"Wobbuffet":	3,
"Abomasnow":	4,
"Absol":	4,
"Aggron":	4,
"Arctovish":	4,
"Aurorus":	4,
"Barbaracle":	4,
"Boltund":	4,
"Carracosta":	4,
"Clawitzer":	4,
"Crustle":	4,
"Cursola":	4,
"Dodrio":	4,
"Drifblim":	4,
"Dubwool":	4,
"Dugtrio":	4,
"Dugtrio-Alola":	4,
"Dusclops":	4,
"Exeggutor-Alola":	4,
"Ferroseed":	4,
"Floatzel":	4,
"Gothitelle":	4,
"Gurdurr":	4,
"Houndoom":	4,
"Kangaskhan":	4,
"Kecleon":	4,
"Komala":	4,
"Lapras":	4,
"Liepard":	4,
"Lurantis":	4,
"Luxray":	4,
"Lycanroc-Midnight":	4,
"Magmortar":	4,
"Mr. Mime-Galar":	4,
"Mr. Rime":	4,
"Oricorio":	4,
"Perrserker":	4,
"Primeape":	4,
"Pyroar":	4,
"Rapidash":	4,
"Regice":	4,
"Regigigas":	4,
"Roselia":	4,
"Sableye":	4,
"Sandslash":	4,
"Sandslash-Alola":	4,
"Stunfisk-Galar":	4,
"Swoobat":	4,
"Throh":	4,
"Togetic":	4,
"Trevenant":	4,
"Abomasnow-Mega":	5,
"Alcremie":	5,
"Ambipom":	5,
"Ampharos-Mega":	5,
"Appletun":	5,
"Archeops":	5,
"Articuno":	5,
"Articuno-Galar":	5,
"Avalugg":	5,
"Braviary":	5,
"Bruxish":	5,
"Centiskorch":	5,
"Cinccino":	5,
"Claydol":	5,
"Coalossal":	5,
"Cryogonal":	5,
"Drampa":	5,
"Drednaw":	5,
"Duraludon":	5,
"Dusknoir":	5,
"Electivire":	5,
"Flapple":	5,
"Frosmoth":	5,
"Gallade":	5,
"Garbodor":	5,
"Golurk":	5,
"Granbull":	5,
"Guzzlord":	5,
"Hitmonchan":	5,
"Honchkrow":	5,
"Jolteon":	5,
"Musharna":	5,
"Ninetales":	5,
"Pincurchin":	5,
"Poliwrath":	5,
"Raichu":	5,
"Rapidash-Galar":	5,
"Regirock":	5,
"Rhydon":	5,
"Rotom-Fan":	5,
"Rotom-Frost":	5,
"Sawk":	5,
"Sceptile":	5,
"Scyther":	5,
"Skuntank":	5,
"Spiritomb":	5,
"Tangela":	5,
"Tauros":	5,
"Type: Null":	5,
"Ursaring":	5,
"Vanilluxe":	5,
"Victreebel":	5,
"Vileplume":	5,
"Xatu":	5,
"Zangoose":	5,
"Absol-Mega":	6,
"Audino":	6,
"Audino-Mega":	6,
"Bewear":	6,
"Braviary":	6,
"Camerupt-Mega":	6,
"Charizard":	6,
"Ditto":	6,
"Doublade":	6,
"Exploud":	6,
"Glalie-Mega":	6,
"Golbat':	6,
"Gourgeist":	6,
"Hitmontop":	6,
"Linoone":	6,
"Ludicolo":	6,
"Machamp":	6,
"Medicham":	6,
"Minior":	6,
"Morpeko":	6,
"Omastar":	6,
"Orbeetle":	6,
"Palossand":	6,
"Passimian":	6,
"Regidrago":	6,
"Rotom":	6,
"Runerigus":	6,
"Sandaconda":	6,
"Stakataka":	6,
"Virizion":	6,
"Yanmega":	6,
"Accelgor":	7,
"Aromatisse":	7,
"Copperajah":	7,
"Delphox":	7,
"Dhelmise":	7,
"Druddigon":	7,
"Eelektross":	7,
"Escavalier":	7,
"Espeon":	7,
"Feraligatr":	7,
"Flygon":	7,
"Forretress":	7,
"Froslass":	7,
"Golisopod":	7,
"Hitmonlee":	7,
"Hoopa":	7,
"Houndoom-Mega":	7,
"Indeedee":	7,
"Kabutops":	7,
"Lanturn":	7,
"Magneton":	7,
"Manectric-Mega":	7,
"Mantine":	7,
"Mismagius":	7,
"Mudsdale":	7,
"Polteageist":	7,
"Quagsire":	7,
"Raichu-Alola":	7,
"Scrafty":	7,
"Sigilyph":	7,
"Sirfetch'd":	7,
"Sneasel":	7,
"Steelix":	7,
"Stunfisk":	7,
"Torkoal":	7,
"Toxicroak":	7,
"Venomoth":	7,
"Weezing":	7,
"Alomomola":	8,
"Arctozolt":	8,
"Chesnaught":	8,
"Cloyster":	8,
"Cofagrigus":	8,
"Diancie":	8,
"Dragalge":	8,
"Durant":	8,
"Emboar":	8,
"Gastrodon":	8,
"Hariyama":	8,
"Lycanroc-Midday":	8,
"Marowak-Alola":	8,
"Miltank":	8,
"Pangoro":	8,
"Persian-Alola":	8,
"Piloswine":	8,
"Qwilfish":	8,
"Rhyperior":	8,
"Ribombee":	8,
"Sceptile-Mega":	8,
"Slurpuff":	8,
"Steelix-Mega":	8,
"Vikavolt":	8,
"Whimsicott":	8,
"Araquanid":	9,
"Bisharp":	9,
"Blastoise":	9,
"Blaziken":	9,
"Breloom":	9,
"Bronzong":	9,
"Comfey":	9,
"Crawdaunt":	9,
"Decidueye":	9,
"Drapion":	9,
"Florges":	9,
"Galvantula":	9,
"Gigalith":	9,
"Glastrier":	9,
"Hatterene":	9,
"Inteleon":	9,
"Jellicent":	9,
"Lickilicky":	9,
"Lucario":	9,
"Manaphy":	9,
"Meloetta":	9,
"Mesprit":	9,
"Mimikyu":	9,
"Moltres-Galar":	9,
"Noivern":	9,
"Politoed":	9,
"Porygon-Z":	9,
"Sharpedo":	9,
"Slowbro-Galar":	9,
"Swellow":	9,
"Tentacruel":	9,
"Tsareena":	9,
"Tyrantrum":	9,
"Venusaur":	9,
"Xurkitree":	9,
"Zoroark":	9,
"Zygarde-10%":	9,
"Aerodactyl":	10,
"Amoonguss":	10,
"Chandelure":	10,
"Chansey":	10,
"Donphan":	10,
"Empoleon":	10,
"Entei":	10,
"Gardevoir":	10,
"Gligar":	10,
"Magnezone":	10,
"Muk-Alola":	10,
"Ninetales-Alola":	10,
"Porygon2":	10,
"Registeel":	10,
"Roserade":	10,
"Rotom-Mow":	10,
"Sableye-Mega":	10,
"Seismitoad":	10,
"Serperior":	10,
"Talonflame":	10,
"Tornadus":	10,
"Umbreon":	10,
"Uxie":	10,
"Vaporeon":	10,
"Weezing-Galar":	10,
"Altaria-Mega":	11,
"Arcanine":	11,
"Barraskewda":	11,
"Blissey":	11,
"Cobalion":	11,
"Cresselia":	11,
"Crobat":	11,
"Goodra":	11,
"Grimmsnarl":	11,
"Heliolisk":	11,
"Heracross":	11,
"Incineroar":	11,
"Kingdra":	11,
"Klefki":	11,
"Moltres":	11,
"Obstagoon":	11,
"Pinsir-Mega":	11,
"Primarina":	11,
"Regieleki":	11,
"Salazzle":	11,
"Sharpedo-Mega":	11,
"Shaymin":	11,
"Staraptor":	11,
"Starmie":	11,
"Toxtricity":	11,
"Beedrill-Mega":	12,
"Blastoise-Mega":	12,
"Celebi":	12,
"Darmanitan":	12,
"Diggersby":	12,
"Dracozolt":	12,
"Gyarados":	12,
"Haxorus":	12,
"Lycanroc-Dusk":	12,
"Mienshao":	12,
"Pelipper":	12,
"Pidgeot-Mega":	12,
"Scolipede":	12,
"Silvally":	12,
"Snorlax":	12,
"Swampert":	12,
"Sylveon":	12,
"Tangrowth":	12,
"Tapu Bulu":	12,
"Tyranitar-Mega":	12,
"Aggron-Mega":	13,
"Alakazam":	13,
"Azelf":	13,
"Azumarill":	13,
"Conkeldurr":	13,
"Heracross-Mega":	13,
"Hippowdon":	13,
"Hoopa-Unbound":	13,
"Kangaskhan-Mega":	13,
"Krookodile":	13,
"Mamoswine":	13,
"Mandibuzz":	13,
"Metagross":	13,
"Milotic":	13,
"Nidoqueen":	13,
"Nihilego":	13,
"Raikou":	13,
"Salamence":	13,
"Slowking":	13,
"Togekiss":	13,
"Tyranitar":	13,
"Venusaur-Mega":	13,
"Volcanion":	13,
"Zarude":	13,
"Blacephalon":	14,
"Charizard-Mega-Y":	14,
"Cinderace":	14,
"Dracovish":	14,
"Ferrothorn":	14,
"Greninja":	14,
"Gyarados-Mega":	14,
"Hawlucha":	14,
"Keldeo":	14,
"Nidoking":	14,
"Reuniclus":	14,
"Rotom-Heat":	14,
"Skarmory":	14,
"Slowbro-Mega":	14,
"Spectrier":	14,
"Suicune":	14,
"Swampert-Mega":	14,
"Thundurus":	14,
"Thundurus-Therian":	14,
"Toxapex":	14,
"Urshifu-Rapid":	14,
"Buzzwole":	15,
"Charizard-Mega-X":	15,
"Corviknight":	15,
"Dragonite":	15,
"Excadrill":	15,
"Garchomp-Mega":	15,
"Gardevoir-Mega":	15,
"Gengar":	15,
"Heatran":	15,
"Infernape":	15,
"Jirachi":	15,
"Kartana":	15,
"Kommo-o":	15,
"Latias":	15,
"Rotom-Wash":	15,
"Scizor":	15,
"Slowbro":	15,
"Slowking-Galar":	15,
"Tapu Lele":	15,
"Terrakion":	15,
"Volcarona":	15,
"Zapdos-Galar":	15,
"Zygarde":	15,
"Aerodactyl-Mega":	16,
"Clefable":	16,
"Darmanitan-Galar":	16,
"Gliscor":	16,
"Hydreigon":	16,
"Kyurem":	16,
"Medicham-Mega":	16,
"Melmetal":	16,
"Rillaboom":	16,
"Tapu Fini":	16,
"Weavile":	16,
"Zeraora":	16,
"Aegislash":	17,
"Celesteela":	17,
"Landorus-Therian":	17,
"Latios":	17,
"Lopunny-Mega":	17,
"Necrozma":	17,
"Tapu Koko":	17,
"Victini":	17,
"Zapdos":	17,
"Diancie-Mega":	18,
"Landorus":	18,
"Gallade-Mega":	18,
"Garchomp":	18,
"Mawile-Mega":	18,
"Scizor-Mega":	18,
"Dragapult":	19,
"Mew":	19,
"Tornadus-Therian":	19}